cfd_python/__init__.py
cfd_python/__init__.pyi
cfd_python/_exceptions.py
cfd_python/_loader.py
cfd_python/_version.py
cfd_python/cfd_python.abi3.so
cfd_python/py.typed
cfd_python-0.1.6.dist-info/METADATA
cfd_python-0.1.6.dist-info/WHEEL
cfd_python-0.1.6.dist-info/RECORD
